refactortool/__init__.py
refactortool/__main__.py
refactortool/analyzer.py
refactortool/refactor.py
refactortool/utils.py
tests/__init__.py
tests/test_analyzer.py
tests/test_refactor.py
tests/test_utils.py
refactortool-0.2.dist-info/LICENCE
refactortool-0.2.dist-info/METADATA
refactortool-0.2.dist-info/WHEEL
refactortool-0.2.dist-info/entry_points.txt
refactortool-0.2.dist-info/top_level.txt
refactortool-0.2.dist-info/RECORD
