Metadata-Version: 2.1
Name: refactortool
Version: 0.2
Summary: A tool for improving code quality by analyzing and refactoring project code.
Home-page: https://github.com/yuna-musashino/refactortool
Author: Yuna Suzuki
Author-email: s2222077@stu.musashino-u.ac.jp
Classifier: Programming Language :: Python :: 3
Classifier: License :: OSI Approved :: MIT License
Classifier: Operating System :: OS Independent
Requires-Python: >=3.6
License-File: LICENCE
Requires-Dist: autopep8
Requires-Dist: pylint
Requires-Dist: black
Requires-Dist: isort
Requires-Dist: flake8
Requires-Dist: pytest
